<?xml version="1.0" encoding="utf-8"?>
<LanguageData>
  <!--The following translations were generated by https://www.deepl.com/-->
  <NVA.CurrentModVersion>已安装的模组版本：{0}</NVA.CurrentModVersion>
  <NVA.ColdFog>寒雾</NVA.ColdFog>
  <NVA.ColdFog.Tooltip>对温度低于{0}的房间启用/禁用冷雾。</NVA.ColdFog.Tooltip>
  <NVA.FogVelocity>雾的速度。{0}</NVA.FogVelocity>
  <NVA.FogVelocity.Tooltip>雾将以这个速度移动。</NVA.FogVelocity.Tooltip>
  <NVA.FogTemp>雾气温度。{0}</NVA.FogTemp>
  <NVA.FogTemp.Tooltip>低于此温度会出现雾气</NVA.FogTemp.Tooltip>
  <NVA.IceLayer>冰层</NVA.IceLayer>
  <NVA.IceLayer.Tooltip>启用/禁用在温度低于{0}的房间形成冰层。</NVA.IceLayer.Tooltip>
  <NVA.BilliardsCue>台球杆</NVA.BilliardsCue>
  <NVA.BilliardsCue.Tooltip>启用/禁用在棋子打牌时显示提示音。</NVA.BilliardsCue.Tooltip>
  <NVA.RainWaterPuddles>水坑</NVA.RainWaterPuddles>
  <NVA.RainWaterPuddles.Tooltip>启用/禁用下雨时形成的水坑。</NVA.RainWaterPuddles.Tooltip>
  <NVA.PuddleChance>水坑的机会 {0}</NVA.PuddleChance>
  <NVA.PuddleChance.Tooltip>水坑在地图上产生的几率（默认为20）。</NVA.PuddleChance.Tooltip>
  <NVA.RainCleanWaterPuddles>清洁的水坑</NVA.RainCleanWaterPuddles>
  <NVA.RainCleanWaterPuddles.Tooltip>启用/禁用清洁家庭区域的未去皮的水坑。</NVA.RainCleanWaterPuddles.Tooltip>
</LanguageData>
